README.txt
setup.py
bimgn/__init__.py
bimgn/bimgn.py
bimgn/test_setup.py
bimgn.egg-info/PKG-INFO
bimgn.egg-info/SOURCES.txt
bimgn.egg-info/dependency_links.txt
bimgn.egg-info/entry_points.txt
bimgn.egg-info/not-zip-safe
bimgn.egg-info/requires.txt
bimgn.egg-info/top_level.txt
bimgn/analysis/__init__.py
bimgn/analysis/analysis.py
bimgn/tests/001_base_config_test.py
bimgn/tests/__init__.py
bimgn/utils/__init__.py
bimgn/utils/logs.py
bimgn/utils/softwares.py
bimgn/utils/utils.py
bimgn/workflow/__init__.py
bimgn/workflow/biotask.py
bimgn/workflow/configuragion.py
bimgn/workflow/it_api.py
bimgn/workflow/build_config/__init__.py