Metadata-Version: 1.2
Name: bimgn
Version: 0.0.10
Summary: Package with bioinformatical utilities
Home-page: https://github.com/Cristian-pg/bimgn
Author: Cristian Perez
Author-email: Vilero89@gmail.com
License: GNU General Public License v3.0
Platform: UNKNOWN
Classifier: Development Status :: 3 - Alpha
Classifier: Programming Language :: Python :: 3
Requires-Python: >=3
